bling/__init__.py
bling/base.py
bling/order.py
bling_integration-0.1.0.dist-info/LICENSE
bling_integration-0.1.0.dist-info/METADATA
bling_integration-0.1.0.dist-info/WHEEL
bling_integration-0.1.0.dist-info/top_level.txt
bling_integration-0.1.0.dist-info/RECORD
