Metadata-Version: 2.1
Name: bling-integration
Version: 0.1.0
Summary: Integração bling
Home-page: https://gitlab.com/vinicius.g.roque/bling
Author: Vinícius Gonçalves Roque
Author-email: vinicius.g.roque@gmail.com
License: UNKNOWN
Platform: UNKNOWN
Requires-Python: >=3.6
Requires-Dist: dicttoxml (>=1.7.4)
